ollama_downloader/__init__.py
ollama_downloader/cli.py
ollama_downloader/sysinfo.py
ollama_downloader/data/__init__.py
ollama_downloader/data/data_models.py
ollama_downloader/downloader/__init__.py
ollama_downloader/downloader/hf_model_downloader.py
ollama_downloader/downloader/model_downloader.py
ollama_downloader/downloader/ollama_model_downloader.py
ollama_downloader-0.2.2.dist-info/METADATA
ollama_downloader-0.2.2.dist-info/WHEEL
ollama_downloader-0.2.2.dist-info/entry_points.txt
ollama_downloader-0.2.2.dist-info/licenses/LICENSE
ollama_downloader-0.2.2.dist-info/RECORD
