Metadata-Version: 2.4
Name: ollama-downloader
Version: 0.2.2
Summary: A library and Hugging Face model downloader for Ollama.
Project-URL: Repository, https://github.com/anirbanbasu/ollama-downloader
Project-URL: Issues, https://github.com/anirbanbasu/ollama-downloader/issues
Project-URL: Download, https://pypi.org/project/ollama-downloader/
Author-email: Anirban Basu <anirbanbasu@users.noreply.github.com>
License-Expression: MIT
License-File: LICENSE
Keywords: downloader,huggingface,huggingface-models,models,ollama,ollama-downloader,ollama-library,ollama-model,tool,web-scraper
Classifier: Development Status :: 5 - Production/Stable
Classifier: Environment :: Console
Classifier: Intended Audience :: Developers
Classifier: Intended Audience :: Science/Research
Classifier: License :: OSI Approved :: MIT License
Classifier: Natural Language :: English
Classifier: Programming Language :: Python :: 3.12
Classifier: Topic :: Utilities
Requires-Python: >=3.12
Requires-Dist: environs>=14.3.0
Requires-Dist: httpx[http2]>=0.28.1
Requires-Dist: lxml>=6.0.0
Requires-Dist: ollama>=0.6.0
Requires-Dist: psutil>=7.0.0
Requires-Dist: pywin32>=311; sys_platform == 'win32'
Requires-Dist: typer>=0.16.0
